fake.cpython-37m-darwin.so
satyrn.cpython-37m-darwin.so
satyrn-0.1.dist-info/LICENSE.txt
satyrn-0.1.dist-info/METADATA
satyrn-0.1.dist-info/WHEEL
satyrn-0.1.dist-info/top_level.txt
satyrn-0.1.dist-info/RECORD
