Metadata-Version: 2.1
Name: satyrn
Version: 0.1
Summary: SAT Solver Interface
Home-page: UNKNOWN
Author: Jeffrey M. Hokanson
Author-email: jeffrey@hokanson.us
License: UNKNOWN
Platform: UNKNOWN
Requires-Dist: pybind11 (>=2.3)
